## 类的加载与连接

[TOC]

### 一、类的加载

**加载：就是将类的.class文件中的二进制数据读入到内存中，将其放在运行时数据区的方法区内，然后在内存中创建一个java.lang.Class对象（规范并未说明Class对象位于哪里，HotSpot虚拟机将其放在了方法区中）用来封装类在方法区内的数据结构。**

- 类的加载的最终产品是位于内存中的**Class对象**
- **Class**对象封装了类在方法区内的数据结构，并且向**Java**程序员提供了访问方法区内的数据结构的接口
- 加载**.class文件的方式**
  1. 从本地系统中直接加载
  2. 通过网络下载**.class**文件
  3. 从**zip**，**jar**等归档文件中加载**.class**文件
  4. 从专有数据库中提取**.class**文件
  5. 将**Java**源文件动态编译为**.class**文件

**类的加载器：有两种类型的类加载器**

- **Java**虚拟机自带的类加载器
  1. <u>根类加载器（Bootstrap）</u>
  2. <u>扩展类加载器（Extension）</u>
  3. <u>系统（应用）类加载器（System）</u>
- 用户自定义的类加载器
  1. **java.lang.ClassLoader**的子类
  2. 用户可以定制类的加载方式

**类加载器并不是要等到某个类被 “首次主动使用” 时再加载它，主动使用我们在后面的章节中将会讲到。**

### 二、JVM规范

- **JVM**规范允许类加载器在预料某个类将要被使用时就预先加载它，如果在预先加载的过程中遇到了**.class**文件缺失或存在错误，类加载器必须在**程序首次主动**使用该类时才报告错误（**LinkageError**错误）
- 如果这个类一直没有被程序主动使用，那么**类加载器就不会报告错误**

### 三、类的连接

**类被加载后，就进入连接阶段。连接就是将已经读入到内存的类的二进制数据合并到虚拟机的运行环境中去。**

- 类的验证的内容
  - 类文件的结构检查：确保使用的是Java类文件的固定格式。
  - 语义检查：确保类符合Java语言的语法规定。
  - 字节码验证：确保字节流可以被JVM安全执行。
  - 二进制兼容性的验证：相互调用的类之间的协调一致。

- 在准备阶段，Java虚拟机为类的静态变量分配内存，并设置默认的初始值。例如对于以下Sample类，在准备阶段，将为int类型的静态变量a分配4个字节的内存空间，并且赋予默认值0，为long类型的静态变量b分配8个字节的内存空间，并且赋予默认值0。

  ```java
  public class Sample {
      private static int a = 1;
      public static long b;
      
      static {
          b = 2;
      }
  }
  ```

- 在解析阶段，将类的二进制数据中的符号引用替换为直接引用
  
  - 符号引用：以一组符号来描述所引用的目标。  （理解：在编译的时候每个java类都会被编译成一个class文件，但在编译的时候虚拟机并不知道所引用的地址，而在这个解析阶段就是为了把符号引用转化成为真正的地址的阶段）
  
    ```java
    public class SymbolicReferences {
        public static void main(String[] args) {
            String s = "abc";
            System.out.println("s = " + s);
        }
    }
    ```
  
    **运行javap -c SymbolicReferences 得到结果如下：**
  
    ```java
    public class com.gapache.commons.jvm.classloader.SymbolicReferences {
      public com.gapache.commons.jvm.classloader.SymbolicReferences();
        Code:
           0: aload_0
           1: invokespecial #1                  // Method java/lang/Object."<init>":()V
           4: return
    
      public static void main(java.lang.String[]);
        Code:
           0: ldc           #2                  // String abc
           2: astore_1
           3: getstatic     #3                  // Field java/lang/System.out:Ljava/io/PrintStream;
           6: new           #4                  // class java/lang/StringBuilder
           9: dup
          10: invokespecial #5                  // Method java/lang/StringBuilder."<init>":()V
          13: ldc           #6                  // String s =
          15: invokevirtual #7                  // Method java/lang/StringBuilder.append:(Ljava/lang/String;)Ljava/lang/StringBuilder;
          18: aload_1
          19: invokevirtual #7                  // Method java/lang/StringBuilder.append:(Ljava/lang/String;)Ljava/lang/StringBuilder;
          22: invokevirtual #8                  // Method java/lang/StringBuilder.toString:()Ljava/lang/String;
          25: invokevirtual #9                  // Method java/io/PrintStream.println:(Ljava/lang/String;)V
          28: return
    }
    ```
  
    这个代码在编译的时候对应的 **s** 会被解析成为符号引用。
  
  - 直接引用：直接引用和虚拟机的布局是相关的，不同的虚拟机对于相同的符号引用所翻译出来的直接引用一般是不同的。如果有了直接引用，那么直接引用的目标一定是被加载到了内存中。
  
    ```java
    public class DirectReferences {
        public static void main(String[] args) {
            System.out.println("s = " + "abc");
        }
    }
    ```
  
    **运行javap -c DirectReferences 得到结果如下：**
  
    ```java
    Compiled from "DirectReferences.java"
    public class com.gapache.commons.jvm.classloader.DirectReferences {
      public com.gapache.commons.jvm.classloader.DirectReferences();
        Code:
           0: aload_0
           1: invokespecial #1                  // Method java/lang/Object."<init>":()V
           4: return
    
      public static void main(java.lang.String[]);
        Code:
           0: getstatic     #2                  // Field java/lang/System.out:Ljava/io/PrintStream;
           3: ldc           #3                  // String s = abc
           5: invokevirtual #4                  // Method java/io/PrintStream.println:(Ljava/lang/String;)V
           8: return
    }
    ```